odoo/addons/product_multi_barcode_constraint_per_company/README.rst
odoo/addons/product_multi_barcode_constraint_per_company/__init__.py
odoo/addons/product_multi_barcode_constraint_per_company/__manifest__.py
odoo/addons/product_multi_barcode_constraint_per_company/i18n/it.po
odoo/addons/product_multi_barcode_constraint_per_company/i18n/product_multi_barcode_constraint_per_company.pot
odoo/addons/product_multi_barcode_constraint_per_company/models/__init__.py
odoo/addons/product_multi_barcode_constraint_per_company/models/product_barcode.py
odoo/addons/product_multi_barcode_constraint_per_company/readme/CONTRIBUTORS.rst
odoo/addons/product_multi_barcode_constraint_per_company/readme/DESCRIPTION.rst
odoo/addons/product_multi_barcode_constraint_per_company/readme/newsfragmensts/.gitkeep
odoo/addons/product_multi_barcode_constraint_per_company/static/description/icon.png
odoo/addons/product_multi_barcode_constraint_per_company/static/description/index.html
odoo/addons/product_multi_barcode_constraint_per_company/tests/__init__.py
odoo/addons/product_multi_barcode_constraint_per_company/tests/test_product_barcode_constraint.py
odoo14_addon_product_multi_barcode_constraint_per_company-14.0.1.0.1.dev5.dist-info/METADATA
odoo14_addon_product_multi_barcode_constraint_per_company-14.0.1.0.1.dev5.dist-info/WHEEL
odoo14_addon_product_multi_barcode_constraint_per_company-14.0.1.0.1.dev5.dist-info/top_level.txt
odoo14_addon_product_multi_barcode_constraint_per_company-14.0.1.0.1.dev5.dist-info/RECORD
