Metadata-Version: 2.1
Name: odoo14-addon-product_multi_barcode_constraint_per_company
Version: 14.0.1.0.1.dev5
Summary: This is a bridge module between "product_multi_barcode" and "product_barcode_constraint_per_company"
Home-page: https://github.com/OCA/stock-logistics-barcode
Author: Ooops, Cetmix, Odoo Community Association (OCA)
Author-email: support@odoo-community.org
License: AGPL-3
Classifier: Programming Language :: Python
Classifier: Framework :: Odoo
Classifier: Framework :: Odoo :: 14.0
Classifier: License :: OSI Approved :: GNU Affero General Public License v3
Requires-Python: >=3.6
Requires-Dist: odoo14-addon-product-barcode-constraint-per-company
Requires-Dist: odoo14-addon-product-multi-barcode
Requires-Dist: odoo<14.1dev,>=14.0a
